pyterri/__init__.py
pyterri/clan.py
pyterri/utils.py
pyterri-0.1.1.dist-info/METADATA
pyterri-0.1.1.dist-info/WHEEL
pyterri-0.1.1.dist-info/top_level.txt
pyterri-0.1.1.dist-info/RECORD
