Metadata-Version: 2.1
Name: pyterri
Version: 0.1.1
Summary: A simple python package for getting territorial.io player and clan data
Home-page: https://github.com/theotherhades/pyterri
Author: theotherhades
Author-email: theotherhades1@gmail.com
License: BSD 2-clause
Requires-Dist: requests
